{
   "update_content":{
      "type":"once",
      "version":8
   },
   "category_common":[
      "Files uploaded by spell4wiki"
   ],
   "language_wise_data":[
      {
         "code":"aa",
         "lang":"Afar",
         "dir":"ltr",
         "local_lang":"Afar"
      },
      {
         "code":"ab",
         "lang":"Abkhazian",
         "dir":"ltr",
         "local_lang":"Аҧсуа"
      },
      {
         "code":"af",
         "lang":"Afrikaans",
         "dir":"ltr",
         "local_lang":"Afrikaans"
      },
      {
         "code":"ak",
         "lang":"Akan",
         "dir":"ltr",
         "local_lang":"Akana"
      },
      {
         "code":"als",
         "lang":"Alemannic",
         "dir":"ltr",
         "local_lang":"Alemannisch"
      },
      {
         "code":"am",
         "lang":"Amharic",
         "dir":"ltr",
         "local_lang":"አማርኛ"
      },
      {
         "code":"an",
         "lang":"Aragonese",
         "dir":"ltr",
         "local_lang":"Aragonés"
      },
      {
         "code":"ang",
         "lang":"Anglo-Saxon / Old English",
         "dir":"ltr",
         "local_lang":"Englisc"
      },
      {
         "code":"ar",
         "lang":"Arabic",
         "dir":"rtl",
         "local_lang":"العربية"
      },
      {
         "code":"arc",
         "lang":"Aramaic",
         "dir":"rtl",
         "local_lang":"ܣܘܪܬ"
      },
      {
         "code":"as",
         "lang":"Assamese",
         "dir":"ltr",
         "local_lang":"অসমীয়া"
      },
      {
         "code":"ast",
         "lang":"Asturian",
         "dir":"ltr",
         "local_lang":"Asturianu"
      },
      {
         "code":"av",
         "lang":"Avar",
         "dir":"ltr",
         "local_lang":"Авар"
      },
      {
         "code":"ay",
         "lang":"Aymara",
         "dir":"ltr",
         "local_lang":"Aymar"
      },
      {
         "code":"az",
         "lang":"Azerbaijani",
         "dir":"ltr",
         "local_lang":"Azərbaycanca / آذربايجان"
      },
      {
         "code":"ba",
         "lang":"Bashkir",
         "dir":"ltr",
         "local_lang":"Башҡорт"
      },
      {
         "code":"bar",
         "lang":"Bavarian",
         "dir":"ltr",
         "local_lang":"Boarisch"
      },
      {
         "code":"bcl",
         "lang":"Bikol",
         "dir":"ltr",
         "local_lang":"Bikol Central"
      },
      {
         "code":"be",
         "lang":"Belarusian",
         "dir":"ltr",
         "local_lang":"Беларуская"
      },
      {
         "code":"bg",
         "lang":"Bulgarian",
         "dir":"ltr",
         "local_lang":"Български"
      },
      {
         "code":"bh",
         "lang":"Bihari",
         "dir":"ltr",
         "local_lang":"भोजपुरी"
      },
      {
         "code":"bi",
         "lang":"Bislama",
         "dir":"ltr",
         "local_lang":"Bislama"
      },
      {
         "code":"bm",
         "lang":"Bambara",
         "dir":"ltr",
         "local_lang":"Bamanankan"
      },
      {
         "code":"bn",
         "lang":"Bengali",
         "dir":"ltr",
         "local_lang":"বাংলা",
         "title_of_words_list":"বিষয়শ্রেণী:বাংলা",
         "category": ["Files uploaded by spell4wiki in bn", "Bengali pronunciation of the words"]
      },
      {
         "code":"bo",
         "lang":"Tibetan",
         "dir":"ltr",
         "local_lang":"བོད་ཡིག / Bod skad"
      },
      {
         "code":"bpy",
         "lang":"Bishnupriya Manipuri",
         "dir":"ltr",
         "local_lang":"ইমার ঠার/বিষ্ণুপ্রিয়া মণিপুরী"
      },
      {
         "code":"br",
         "lang":"Breton",
         "dir":"ltr",
         "local_lang":"Brezhoneg"
      },
      {
         "code":"bs",
         "lang":"Bosnian",
         "dir":"ltr",
         "local_lang":"Bosanski"
      },
      {
         "code":"bug",
         "lang":"Buginese",
         "dir":"ltr",
         "local_lang":"ᨅᨔ ᨕᨘᨁᨗ / Basa Ugi"
      },
      {
         "code":"bxr",
         "lang":"Buriat (Russia)",
         "dir":"ltr",
         "local_lang":"Буряад хэлэн"
      },
      {
         "code":"ca",
         "lang":"Catalan",
         "dir":"ltr",
         "local_lang":"Català"
      },
      {
         "code":"cdo",
         "lang":"Min Dong Chinese",
         "dir":"ltr",
         "local_lang":"Mìng-dĕ̤ng-ngṳ̄ / 閩東語"
      },
      {
         "code":"ce",
         "lang":"Chechen",
         "dir":"ltr",
         "local_lang":"Нохчийн"
      },
      {
         "code":"ceb",
         "lang":"Cebuano",
         "dir":"ltr",
         "local_lang":"Sinugboanong Binisaya"
      },
      {
         "code":"ch",
         "lang":"Chamorro",
         "dir":"ltr",
         "local_lang":"Chamoru"
      },
      {
         "code":"cho",
         "lang":"Choctaw",
         "dir":"ltr",
         "local_lang":"Choctaw"
      },
      {
         "code":"chr",
         "lang":"Cherokee",
         "dir":"ltr",
         "local_lang":"ᏣᎳᎩ"
      },
      {
         "code":"chy",
         "lang":"Cheyenne",
         "dir":"ltr",
         "local_lang":"Tsetsêhestâhese"
      },
      {
         "code":"co",
         "lang":"Corsican",
         "dir":"ltr",
         "local_lang":"Corsu"
      },
      {
         "code":"cr",
         "lang":"Cree",
         "dir":"ltr",
         "local_lang":"Nehiyaw"
      },
      {
         "code":"cs",
         "lang":"Czech",
         "dir":"ltr",
         "local_lang":"Česky"
      },
      {
         "code":"csb",
         "lang":"Kashubian",
         "dir":"ltr",
         "local_lang":"Kaszëbsczi"
      },
      {
         "code":"cu",
         "lang":"Old Church Slavonic / Old Bulgarian",
         "dir":"ltr",
         "local_lang":"словѣньскъ / slověnĭskŭ"
      },
      {
         "code":"cv",
         "lang":"Chuvash",
         "dir":"ltr",
         "local_lang":"Чăваш"
      },
      {
         "code":"cy",
         "lang":"Welsh",
         "dir":"ltr",
         "local_lang":"Cymraeg"
      },
      {
         "code":"da",
         "lang":"Danish",
         "dir":"ltr",
         "local_lang":"Dansk"
      },
      {
         "code":"dag",
         "lang":"Dagbani",
         "dir":"ltr",
         "local_lang":"Dagbanli",
         "category": ["Files uploaded by spell4wiki in dag", "Dagbani words"]
      },
      {
         "code":"de",
         "lang":"German",
         "dir":"ltr",
         "local_lang":"Deutsch",
         "title_of_words_list":"Category:Nachname (Deutsch)",
         "category": ["Files uploaded by spell4wiki in de", "German pronunciation"] 
      },
      {
         "code":"diq",
         "lang":"Dimli",
         "dir":"ltr",
         "local_lang":"Zazaki"
      },
      {
         "code":"dsb",
         "lang":"Lower Sorbian",
         "dir":"ltr",
         "local_lang":"Dolnoserbski"
      },
      {
         "code":"dv",
         "lang":"Divehi",
         "dir":"rtl",
         "local_lang":"ދިވެހިބަސް"
      },
      {
         "code":"dz",
         "lang":"Dzongkha",
         "dir":"ltr",
         "local_lang":"ཇོང་ཁ"
      },
      {
         "code":"ee",
         "lang":"Ewe",
         "dir":"ltr",
         "local_lang":"Ɛʋɛ"
      },
      {
         "code":"el",
         "lang":"Greek",
         "dir":"ltr",
         "local_lang":"Ελληνικά"
      },
      {
         "code":"en",
         "lang":"English",
         "dir":"ltr",
         "local_lang":"English"
      },
      {
         "code":"eo",
         "lang":"Esperanto",
         "dir":"ltr",
         "local_lang":"Esperanto"
      },
      {
         "code":"es",
         "lang":"Spanish",
         "dir":"ltr",
         "local_lang":"Español"
      },
      {
         "code":"et",
         "lang":"Estonian",
         "dir":"ltr",
         "local_lang":"Eesti"
      },
      {
         "code":"eu",
         "lang":"Basque",
         "dir":"ltr",
         "local_lang":"Euskara"
      },
      {
         "code":"ext",
         "lang":"Extremaduran",
         "dir":"ltr",
         "local_lang":"Estremeñu"
      },
      {
         "code":"fa",
         "lang":"Persian",
         "dir":"rtl",
         "local_lang":"فارسی"
      },
      {
         "code":"ff",
         "lang":"Peul",
         "dir":"ltr",
         "local_lang":"Fulfulde"
      },
      {
         "code":"fi",
         "lang":"Finnish",
         "dir":"ltr",
         "local_lang":"Suomi"
      },
      {
         "code":"fj",
         "lang":"Fijian",
         "dir":"ltr",
         "local_lang":"Na Vosa Vakaviti"
      },
      {
         "code":"fo",
         "lang":"Faroese",
         "dir":"ltr",
         "local_lang":"Føroyskt"
      },
      {
         "code":"fr",
         "lang":"French",
         "dir":"ltr",
         "local_lang":"Français"
      },
      {
         "code":"frp",
         "lang":"Arpitan / Franco-Provençal",
         "dir":"ltr",
         "local_lang":"Arpitan / francoprovençal"
      },
      {
         "code":"fur",
         "lang":"Friulian",
         "dir":"ltr",
         "local_lang":"Furlan"
      },
      {
         "code":"fy",
         "lang":"West Frisian",
         "dir":"ltr",
         "local_lang":"Frysk"
      },
      {
         "code":"ga",
         "lang":"Irish",
         "dir":"ltr",
         "local_lang":"Gaeilge"
      },
      {
         "code":"gan",
         "lang":"Gan Chinese",
         "dir":"ltr",
         "local_lang":"贛語"
      },
      {
         "code":"gbm",
         "lang":"Garhwali",
         "dir":"ltr",
         "local_lang":"गढ़वळी"
      },
      {
         "code":"gd",
         "lang":"Scottish Gaelic",
         "dir":"ltr",
         "local_lang":"Gàidhlig"
      },
      {
         "code":"gil",
         "lang":"Gilbertese",
         "dir":"ltr",
         "local_lang":"Taetae ni kiribati"
      },
      {
         "code":"gl",
         "lang":"Galician",
         "dir":"ltr",
         "local_lang":"Galego"
      },
      {
         "code":"gn",
         "lang":"Guarani",
         "dir":"ltr",
         "local_lang":"Avañe'ẽ"
      },
      {
         "code":"got",
         "lang":"Gothic",
         "dir":"ltr",
         "local_lang":"gutisk"
      },
      {
         "code":"gu",
         "lang":"Gujarati",
         "dir":"ltr",
         "local_lang":"ગુજરાતી"
      },
      {
         "code":"gv",
         "lang":"Manx",
         "dir":"ltr",
         "local_lang":"Gaelg"
      },
      {
         "code":"ha",
         "lang":"Hausa",
         "dir":"rtl",
         "local_lang":"هَوُسَ"
      },
      {
         "code":"hak",
         "lang":"Hakka Chinese",
         "dir":"ltr",
         "local_lang":"客家語/Hak-kâ-ngî"
      },
      {
         "code":"haw",
         "lang":"Hawaiian",
         "dir":"ltr",
         "local_lang":"Hawai`i"
      },
      {
         "code":"he",
         "lang":"Hebrew",
         "dir":"rtl",
         "local_lang":"עברית"
      },
      {
         "code":"hi",
         "lang":"Hindi",
         "dir":"ltr",
         "local_lang":"हिन्दी"
      },
      {
         "code":"ho",
         "lang":"Hiri Motu",
         "dir":"ltr",
         "local_lang":"Hiri Motu"
      },
      {
         "code":"hr",
         "lang":"Croatian",
         "dir":"ltr",
         "local_lang":"Hrvatski"
      },
      {
         "code":"ht",
         "lang":"Haitian",
         "dir":"ltr",
         "local_lang":"Krèyol ayisyen"
      },
      {
         "code":"hu",
         "lang":"Hungarian",
         "dir":"ltr",
         "local_lang":"Magyar"
      },
      {
         "code":"hy",
         "lang":"Armenian",
         "dir":"ltr",
         "local_lang":"Հայերեն"
      },
      {
         "code":"hz",
         "lang":"Herero",
         "dir":"ltr",
         "local_lang":"Otsiherero"
      },
      {
         "code":"ia",
         "lang":"Interlingua",
         "dir":"ltr",
         "local_lang":"Interlingua"
      },
      {
         "code":"id",
         "lang":"Indonesian",
         "dir":"ltr",
         "local_lang":"Bahasa Indonesia"
      },
      {
         "code":"ie",
         "lang":"Interlingue",
         "dir":"ltr",
         "local_lang":"Interlingue"
      },
      {
         "code":"ig",
         "lang":"Igbo",
         "dir":"ltr",
         "local_lang":"Igbo"
      },
      {
         "code":"ii",
         "lang":"Sichuan Yi",
         "dir":"ltr",
         "local_lang":"ꆇꉙ / 四川彝语"
      },
      {
         "code":"ik",
         "lang":"Inupiak",
         "dir":"ltr",
         "local_lang":"Iñupiak"
      },
      {
         "code":"ilo",
         "lang":"Ilokano",
         "dir":"ltr",
         "local_lang":"Ilokano"
      },
      {
         "code":"inh",
         "lang":"Ingush",
         "dir":"ltr",
         "local_lang":"ГӀалгӀай"
      },
      {
         "code":"io",
         "lang":"Ido",
         "dir":"ltr",
         "local_lang":"Ido"
      },
      {
         "code":"is",
         "lang":"Icelandic",
         "dir":"ltr",
         "local_lang":"Íslenska"
      },
      {
         "code":"it",
         "lang":"Italian",
         "dir":"ltr",
         "local_lang":"Italiano"
      },
      {
         "code":"iu",
         "lang":"Inuktitut",
         "dir":"ltr",
         "local_lang":"ᐃᓄᒃᑎᑐᑦ"
      },
      {
         "code":"ja",
         "lang":"Japanese",
         "dir":"ltr",
         "local_lang":"日本語"
      },
      {
         "code":"jbo",
         "lang":"Lojban",
         "dir":"ltr",
         "local_lang":"Lojban"
      },
      {
         "code":"jv",
         "lang":"Javanese",
         "dir":"ltr",
         "local_lang":"Basa Jawa"
      },
      {
         "code":"ka",
         "lang":"Georgian",
         "dir":"ltr",
         "local_lang":"ქართული"
      },
      {
         "code":"kg",
         "lang":"Kongo",
         "dir":"ltr",
         "local_lang":"KiKongo"
      },
      {
         "code":"ki",
         "lang":"Kikuyu",
         "dir":"ltr",
         "local_lang":"Gĩkũyũ"
      },
      {
         "code":"kj",
         "lang":"Kuanyama",
         "dir":"ltr",
         "local_lang":"Kuanyama"
      },
      {
         "code":"kk",
         "lang":"Kazakh",
         "dir":"ltr",
         "local_lang":"Қазақша"
      },
      {
         "code":"kl",
         "lang":"Greenlandic",
         "dir":"ltr",
         "local_lang":"Kalaallisut"
      },
      {
         "code":"km",
         "lang":"Cambodian",
         "dir":"ltr",
         "local_lang":"ភាសាខ្មែរ"
      },
      {
         "code":"kn",
         "lang":"Kannada",
         "dir":"ltr",
         "local_lang":"ಕನ್ನಡ",
         "title_of_words_list":"ವರ್ಗ:ನಾಮಪದಗಳು",
         "category": ["Files uploaded by spell4wiki in kn"]
      },
      {
         "code":"khw",
         "lang":"Khowar",
         "dir":"rtl",
         "local_lang":"کھوار"
      },
      {
         "code":"ko",
         "lang":"Korean",
         "dir":"ltr",
         "local_lang":"한국어"
      },
      {
         "code":"kr",
         "lang":"Kanuri",
         "dir":"ltr",
         "local_lang":"Kanuri"
      },
      {
         "code":"ks",
         "lang":"Kashmiri",
         "dir":"rtl",
         "local_lang":"कश्मीरी / كشميري"
      },
      {
         "code":"ksh",
         "lang":"Ripuarian",
         "dir":"ltr",
         "local_lang":"Ripoarisch"
      },
      {
         "code":"ku",
         "lang":"Kurdish",
         "dir":"rtl",
         "local_lang":"Kurdî / كوردی"
      },
      {
         "code":"kv",
         "lang":"Komi",
         "dir":"ltr",
         "local_lang":"Коми"
      },
      {
         "code":"kw",
         "lang":"Cornish",
         "dir":"ltr",
         "local_lang":"Kernewek"
      },
      {
         "code":"ky",
         "lang":"Kirghiz",
         "dir":"ltr",
         "local_lang":"Kırgızca / Кыргызча"
      },
      {
         "code":"la",
         "lang":"Latin",
         "dir":"ltr",
         "local_lang":"Latina"
      },
      {
         "code":"lad",
         "lang":"Ladino / Judeo-Spanish",
         "dir":"ltr",
         "local_lang":"Dzhudezmo / Djudeo-Espanyol"
      },
      {
         "code":"lan",
         "lang":"Lango",
         "dir":"ltr",
         "local_lang":"Leb Lango / Luo"
      },
      {
         "code":"lb",
         "lang":"Luxembourgish",
         "dir":"ltr",
         "local_lang":"Lëtzebuergesch"
      },
      {
         "code":"lg",
         "lang":"Ganda",
         "dir":"ltr",
         "local_lang":"Luganda"
      },
      {
         "code":"li",
         "lang":"Limburgian",
         "dir":"ltr",
         "local_lang":"Limburgs"
      },
      {
         "code":"lij",
         "lang":"Ligurian",
         "dir":"ltr",
         "local_lang":"Líguru"
      },
      {
         "code":"lmo",
         "lang":"Lombard",
         "dir":"ltr",
         "local_lang":"Lumbaart"
      },
      {
         "code":"ln",
         "lang":"Lingala",
         "dir":"ltr",
         "local_lang":"Lingála"
      },
      {
         "code":"lo",
         "lang":"Laotian",
         "dir":"ltr",
         "local_lang":"ລາວ / Pha xa lao"
      },
      {
         "code":"lzz",
         "lang":"Laz",
         "dir":"ltr",
         "local_lang":"Lazuri / ლაზური"
      },
      {
         "code":"lt",
         "lang":"Lithuanian",
         "dir":"ltr",
         "local_lang":"Lietuvių"
      },
      {
         "code":"lv",
         "lang":"Latvian",
         "dir":"ltr",
         "local_lang":"Latviešu"
      },
      {
         "code":"mg",
         "lang":"Malagasy",
         "dir":"ltr",
         "local_lang":"Malagasy"
      },
      {
         "code":"man",
         "lang":"Mandarin",
         "dir":"ltr",
         "local_lang":"官話/官话"
      },
      {
         "code":"mh",
         "lang":"Marshallese",
         "dir":"ltr",
         "local_lang":"Kajin Majel / Ebon"
      },
      {
         "code":"mi",
         "lang":"Maori",
         "dir":"ltr",
         "local_lang":"Māori"
      },
      {
         "code":"min",
         "lang":"Minangkabau",
         "dir":"ltr",
         "local_lang":"Minangkabau"
      },
      {
         "code":"mk",
         "lang":"Macedonian",
         "dir":"ltr",
         "local_lang":"Македонски"
      },
      {
         "code":"ml",
         "lang":"Malayalam",
         "dir":"ltr",
         "local_lang":"മലയാളം"
      },
      {
         "code":"mn",
         "lang":"Mongolian",
         "dir":"ltr",
         "local_lang":"Монгол"
      },
      {
         "code":"mo",
         "lang":"Moldovan",
         "dir":"ltr",
         "local_lang":"Moldovenească"
      },
      {
         "code":"mr",
         "lang":"Marathi",
         "dir":"ltr",
         "local_lang":"मराठी"
      },
      {
         "code":"ms",
         "lang":"Malay",
         "dir":"ltr",
         "local_lang":"Bahasa Melayu"
      },
      {
         "code":"mt",
         "lang":"Maltese",
         "dir":"ltr",
         "local_lang":"bil-Malti"
      },
      {
         "code":"mus",
         "lang":"Creek / Muskogee",
         "dir":"ltr",
         "local_lang":"Mvskoke"
      },
      {
         "code":"mwl",
         "lang":"Mirandese",
         "dir":"ltr",
         "local_lang":"Mirandés"
      },
      {
         "code":"my",
         "lang":"Burmese",
         "dir":"ltr",
         "local_lang":"Myanmasa"
      },
      {
         "code":"na",
         "lang":"Nauruan",
         "dir":"ltr",
         "local_lang":"Dorerin Naoero"
      },
      {
         "code":"nah",
         "lang":"Nahuatl",
         "dir":"ltr",
         "local_lang":"Nahuatl"
      },
      {
         "code":"nap",
         "lang":"Neapolitan",
         "dir":"ltr",
         "local_lang":"Nnapulitano"
      },
      {
         "code":"nd",
         "lang":"North Ndebele",
         "dir":"ltr",
         "local_lang":"Sindebele"
      },
      {
         "code":"nds",
         "lang":"Low German / Low Saxon",
         "dir":"ltr",
         "local_lang":"Plattdüütsch"
      },
      {
         "code":"ne",
         "lang":"Nepali",
         "dir":"ltr",
         "local_lang":"नेपाली"
      },
      {
         "code":"new",
         "lang":"Newar",
         "dir":"ltr",
         "local_lang":"नेपालभाषा / Newah Bhaye"
      },
      {
         "code":"ng",
         "lang":"Ndonga",
         "dir":"ltr",
         "local_lang":"Oshiwambo"
      },
      {
         "code":"nl",
         "lang":"Dutch",
         "dir":"ltr",
         "local_lang":"Nederlands"
      },
      {
         "code":"nn",
         "lang":"Norwegian Nynorsk",
         "dir":"ltr",
         "local_lang":"Norsk (nynorsk)"
      },
      {
         "code":"no",
         "lang":"Norwegian",
         "dir":"ltr",
         "local_lang":"Norsk (bokmål / riksmål)"
      },
      {
         "code":"nr",
         "lang":"South Ndebele",
         "dir":"ltr",
         "local_lang":"isiNdebele"
      },
      {
         "code":"nso",
         "lang":"Northern Sotho",
         "dir":"ltr",
         "local_lang":"Sesotho sa Leboa / Sepedi"
      },
      {
         "code":"nrm",
         "lang":"Norman",
         "dir":"ltr",
         "local_lang":"Nouormand / Normaund"
      },
      {
         "code":"nv",
         "lang":"Navajo",
         "dir":"ltr",
         "local_lang":"Diné bizaad"
      },
      {
         "code":"ny",
         "lang":"Chichewa",
         "dir":"ltr",
         "local_lang":"Chi-Chewa"
      },
      {
         "code":"oc",
         "lang":"Occitan",
         "dir":"ltr",
         "local_lang":"Occitan"
      },
      {
         "code":"oj",
         "lang":"Ojibwa",
         "dir":"ltr",
         "local_lang":"ᐊᓂᔑᓈᐯᒧᐎᓐ / Anishinaabemowin"
      },
      {
         "code":"om",
         "lang":"Oromo",
         "dir":"ltr",
         "local_lang":"Oromoo"
      },
      {
         "code":"or",
         "lang":"Oriya",
         "dir":"ltr",
         "local_lang":"ଓଡ଼ିଆ"
      },
      {
         "code":"os",
         "lang":"Ossetian / Ossetic",
         "dir":"ltr",
         "local_lang":"Иронау"
      },
      {
         "code":"pa",
         "lang":"Panjabi / Punjabi",
         "dir":"ltr",
         "local_lang":"ਪੰਜਾਬੀ / पंजाबी / پنجابي"
      },
      {
         "code":"pag",
         "lang":"Pangasinan",
         "dir":"ltr",
         "local_lang":"Pangasinan"
      },
      {
         "code":"pam",
         "lang":"Kapampangan",
         "dir":"ltr",
         "local_lang":"Kapampangan"
      },
      {
         "code":"pap",
         "lang":"Papiamentu",
         "dir":"ltr",
         "local_lang":"Papiamentu"
      },
      {
         "code":"pdc",
         "lang":"Pennsylvania German",
         "dir":"ltr",
         "local_lang":"Deitsch"
      },
      {
         "code":"pi",
         "lang":"Pali",
         "dir":"ltr",
         "local_lang":"Pāli / पाऴि"
      },
      {
         "code":"pih",
         "lang":"Norfolk",
         "dir":"ltr",
         "local_lang":"Norfuk"
      },
      {
         "code":"pl",
         "lang":"Polish",
         "dir":"ltr",
         "local_lang":"Polski"
      },
      {
         "code":"pms",
         "lang":"Piedmontese",
         "dir":"ltr",
         "local_lang":"Piemontèis"
      },
      {
         "code":"ps",
         "lang":"Pashto",
         "dir":"rtl",
         "local_lang":"پښتو"
      },
      {
         "code":"pt",
         "lang":"Portuguese",
         "dir":"ltr",
         "local_lang":"Português"
      },
      {
         "code":"qu",
         "lang":"Quechua",
         "dir":"ltr",
         "local_lang":"Runa Simi"
      },
      {
         "code":"rm",
         "lang":"Raeto Romance",
         "dir":"ltr",
         "local_lang":"Rumantsch"
      },
      {
         "code":"rmy",
         "lang":"Romani",
         "dir":"ltr",
         "local_lang":"Romani / रोमानी"
      },
      {
         "code":"rn",
         "lang":"Kirundi",
         "dir":"ltr",
         "local_lang":"Kirundi"
      },
      {
         "code":"ro",
         "lang":"Romanian",
         "dir":"ltr",
         "local_lang":"Română"
      },
      {
         "code":"ru",
         "lang":"Russian",
         "dir":"ltr",
         "local_lang":"Русский",
         "title_of_words_list":"Категория:Животные/ru",
         "category": ["Files uploaded by spell4wiki in ru", "Russian pronunciation"]
      },
      {
         "code":"rw",
         "lang":"Rwandi",
         "dir":"ltr",
         "local_lang":"Kinyarwandi"
      },
      {
         "code":"sa",
         "lang":"Sanskrit",
         "dir":"ltr",
         "local_lang":"संस्कृतम्"
      },
      {
         "code":"sc",
         "lang":"Sardinian",
         "dir":"ltr",
         "local_lang":"Sardu"
      },
      {
         "code":"scn",
         "lang":"Sicilian",
         "dir":"ltr",
         "local_lang":"Sicilianu"
      },
      {
         "code":"sco",
         "lang":"Scots",
         "dir":"ltr",
         "local_lang":"Scots"
      },
      {
         "code":"sd",
         "lang":"Sindhi",
         "dir":"ltr",
         "local_lang":"सिनधि"
      },
      {
         "code":"se",
         "lang":"Northern Sami",
         "dir":"ltr",
         "local_lang":"Davvisámegiella"
      },
      {
         "code":"sg",
         "lang":"Sango",
         "dir":"ltr",
         "local_lang":"Sängö"
      },
      {
         "code":"sh",
         "lang":"Serbo-Croatian",
         "dir":"ltr",
         "local_lang":"Srpskohrvatski / Српскохрватски"
      },
      {
         "code":"si",
         "lang":"Sinhalese",
         "dir":"ltr",
         "local_lang":"සිංහල"
      },
      {
         "code":"sk",
         "lang":"Slovak",
         "dir":"ltr",
         "local_lang":"Slovenčina"
      },
      {
         "code":"sl",
         "lang":"Slovenian",
         "dir":"ltr",
         "local_lang":"Slovenščina"
      },
      {
         "code":"sm",
         "lang":"Samoan",
         "dir":"ltr",
         "local_lang":"Gagana Samoa"
      },
      {
         "code":"sn",
         "lang":"Shona",
         "dir":"ltr",
         "local_lang":"chiShona"
      },
      {
         "code":"so",
         "lang":"Somalia",
         "dir":"ltr",
         "local_lang":"Soomaaliga"
      },
      {
         "code":"sq",
         "lang":"Albanian",
         "dir":"ltr",
         "local_lang":"Shqip"
      },
      {
         "code":"sr",
         "lang":"Serbian",
         "dir":"ltr",
         "local_lang":"Српски"
      },
      {
         "code":"ss",
         "lang":"Swati",
         "dir":"ltr",
         "local_lang":"SiSwati"
      },
      {
         "code":"st",
         "lang":"Southern Sotho",
         "dir":"ltr",
         "local_lang":"Sesotho"
      },
      {
         "code":"su",
         "lang":"Sundanese",
         "dir":"ltr",
         "local_lang":"Basa Sunda"
      },
      {
         "code":"sv",
         "lang":"Swedish",
         "dir":"ltr",
         "local_lang":"Svenska",
         "title_of_words_list":"Kategori:Svenska/Alla uppslag",
         "category": ["Files uploaded by spell4wiki in sv"]
      },
      {
         "code":"sw",
         "lang":"Swahili",
         "dir":"ltr",
         "local_lang":"Kiswahili"
      },
      {
         "code":"ta",
         "lang":"Tamil",
         "dir":"ltr",
         "local_lang":"தமிழ்",
         "title_of_words_list":"பகுப்பு:தமிழ்-ஒலிக்கோப்புகளில்லை",
         "category": ["Files uploaded by spell4wiki in ta", "Tamil pronunciation of the words with Tamil script"]
      },
      {
         "code":"te",
         "lang":"Telugu",
         "dir":"ltr",
         "local_lang":"తెలుగు"
      },
      {
         "code":"tet",
         "lang":"Tetum",
         "dir":"ltr",
         "local_lang":"Tetun"
      },
      {
         "code":"tg",
         "lang":"Tajik",
         "dir":"ltr",
         "local_lang":"Тоҷикӣ"
      },
      {
         "code":"th",
         "lang":"Thai",
         "dir":"ltr",
         "local_lang":"ไทย / Phasa Thai"
      },
      {
         "code":"ti",
         "lang":"Tigrinya",
         "dir":"ltr",
         "local_lang":"ትግርኛ"
      },
      {
         "code":"tk",
         "lang":"Turkmen",
         "dir":"ltr",
         "local_lang":"Туркмен / تركمن"
      },
      {
         "code":"tl",
         "lang":"Tagalog",
         "dir":"ltr",
         "local_lang":"Tagalog"
      },
      {
         "code":"tlh",
         "lang":"Klingon",
         "dir":"ltr",
         "local_lang":"tlhIngan-Hol"
      },
      {
         "code":"tn",
         "lang":"Tswana",
         "dir":"ltr",
         "local_lang":"Setswana"
      },
      {
         "code":"to",
         "lang":"Tonga",
         "dir":"ltr",
         "local_lang":"Lea Faka-Tonga"
      },
      {
         "code":"tpi",
         "lang":"Tok Pisin",
         "dir":"ltr",
         "local_lang":"Tok Pisin"
      },
      {
         "code":"tr",
         "lang":"Turkish",
         "dir":"ltr",
         "local_lang":"Türkçe"
      },
      {
         "code":"ts",
         "lang":"Tsonga",
         "dir":"ltr",
         "local_lang":"Xitsonga"
      },
      {
         "code":"tt",
         "lang":"Tatar",
         "dir":"ltr",
         "local_lang":"Tatarça"
      },
      {
         "code":"tum",
         "lang":"Tumbuka",
         "dir":"ltr",
         "local_lang":"chiTumbuka"
      },
      {
         "code":"tw",
         "lang":"Twi",
         "dir":"ltr",
         "local_lang":"Twi"
      },
      {
         "code":"ty",
         "lang":"Tahitian",
         "dir":"ltr",
         "local_lang":"Reo Mā`ohi"
      },
      {
         "code":"udm",
         "lang":"Udmurt",
         "dir":"ltr",
         "local_lang":"Удмурт кыл"
      },
      {
         "code":"ug",
         "lang":"Uyghur",
         "dir":"ltr",
         "local_lang":"Uyƣurqə / ئۇيغۇرچە"
      },
      {
         "code":"uk",
         "lang":"Ukrainian",
         "dir":"ltr",
         "local_lang":"Українська"
      },
      {
         "code":"ur",
         "lang":"Urdu",
         "dir":"rtl",
         "local_lang":"اردو"
      },
      {
         "code":"uz",
         "lang":"Uzbek",
         "dir":"ltr",
         "local_lang":"Ўзбек"
      },
      {
         "code":"ve",
         "lang":"Venda",
         "dir":"ltr",
         "local_lang":"Tshivenḓa"
      },
      {
         "code":"vi",
         "lang":"Vietnamese",
         "dir":"ltr",
         "local_lang":"Việtnam"
      },
      {
         "code":"vec",
         "lang":"Venetian",
         "dir":"ltr",
         "local_lang":"Vèneto"
      },
      {
         "code":"vls",
         "lang":"West Flemish",
         "dir":"ltr",
         "local_lang":"West-Vlaoms"
      },
      {
         "code":"vo",
         "lang":"Volapük",
         "dir":"ltr",
         "local_lang":"Volapük"
      },
      {
         "code":"wa",
         "lang":"Walloon",
         "dir":"ltr",
         "local_lang":"Walon"
      },
      {
         "code":"war",
         "lang":"Waray / Samar-Leyte Visayan",
         "dir":"ltr",
         "local_lang":"Winaray / Binisaya Lineyte-Samarnon"
      },
      {
         "code":"wo",
         "lang":"Wolof",
         "dir":"ltr",
         "local_lang":"Wollof"
      },
      {
         "code":"xal",
         "lang":"Kalmyk",
         "dir":"ltr",
         "local_lang":"Хальмг"
      },
      {
         "code":"xh",
         "lang":"Xhosa",
         "dir":"ltr",
         "local_lang":"isiXhosa"
      },
      {
         "code":"xmf",
         "lang":"Megrelian",
         "dir":"ltr",
         "local_lang":"მარგალური"
      },
      {
         "code":"yi",
         "lang":"Yiddish",
         "dir":"rtl",
         "local_lang":"ייִדיש"
      },
      {
         "code":"yo",
         "lang":"Yoruba",
         "dir":"ltr",
         "local_lang":"Yorùbá"
      },
      {
         "code":"za",
         "lang":"Zhuang",
         "dir":"ltr",
         "local_lang":"Cuengh / Tôô / 壮语"
      },
      {
         "code":"zh",
         "lang":"Chinese",
         "dir":"ltr",
         "local_lang":"中文"
      },
      {
         "code":"yue",
         "lang":"Cantonese",
         "dir":"ltr",
         "local_lang":"粵語 / 粤语"
      },
      {
         "code":"zu",
         "lang":"Zulu",
         "dir":"ltr",
         "local_lang":"isiZulu"
      }
   ]
}
